MANIFEST.in
README.md
setup.py
dframe/__init__.py
dframe/errors.py
dframe.egg-info/PKG-INFO
dframe.egg-info/SOURCES.txt
dframe.egg-info/dependency_links.txt
dframe.egg-info/not-zip-safe
dframe.egg-info/requires.txt
dframe.egg-info/top_level.txt
dframe/array/__init__.py
dframe/array/array.py
dframe/compat/__init__.py
dframe/compat/compat.py
dframe/dataframe/__init__.py
dframe/dataframe/dataframe.py
dframe/dataframe/operations.py
dframe/dtypes/__init__.py
dframe/dtypes/dtypes.py
dframe/missing/__init__.py
dframe/missing/element_operations.py
dframe/scalar/__init__.py
dframe/scalar/iterables.py
dframe/scalar/lists.py
dframe/scalar/scalar.py
dframe/tests/test_array.py
dframe/tests/test_dataframe_alternate_constructors.py
dframe/tests/test_dataframe_creation.py
dframe/tests/test_dataframe_list_single_indexing.py
dframe/tests/test_dataframe_scalar_list_dual_indexing.py
dframe/tests/test_dataframe_scalar_scalar_dual_indexing.py
dframe/tests/test_dataframe_scalar_single_indexing.py
dframe/tests/test_dataframe_scalar_slice_dual_indexing.py
dframe/tests/test_dataframe_slice_single_indexing.py