Metadata-Version: 1.1
Name: dframe
Version: 0.1.6
Summary: Easy-to-use, indexless dataframe data structure in Python.
Home-page: http://github.com/ankur-gupta/dframe
Author: Ankur Gupta
Author-email: ankur@perfectlyrandom.org
License: UNKNOWN
Keywords: dataframe indexless
Platform: UNKNOWN
Classifier: Development Status :: 3 - Alpha
Classifier: Programming Language :: Python :: 2.7
